{"gates": [
  {
    "output": false,
    "name": "gate3",
    "x": 404,
    "y": 404,
    "type": "input",
    "connections": [{
      "destId": "gate1",
      "destIndex": 1
    }]
  },
  {
    "output": false,
    "name": "gate0",
    "x": 384,
    "y": 283,
    "type": "input",
    "connections": [{
      "destId": "gate1",
      "destIndex": 0
    }]
  },
  {
    "name": "gate2",
    "x": 709,
    "y": 350,
    "type": "output",
    "connections": []
  },
  {
    "name": "gate1",
    "x": 524,
    "y": 328,
    "type": "AND",
    "connections": [{
      "destId": "gate2",
      "destIndex": 0
    }]
  }
]}